dnsprobe/__init__.py
dnsprobe/cmds/__init__.py
dnsprobe/cmds/config.py
dnsprobe/cmds/nameservers.py
dnsprobe/deamon/__init__.py
dnsprobe/deamon/multislot.py
dnsprobe/deamon/tempCodeRunnerFile.py
dnsprobe/utils/__init__.py
dnsprobe/utils/attribute.py
dnsprobe/utils/config.py
dnsprobe/utils/nameservers.py
dnsprobe/utils/prober.py
dnsprobe-0.2.dist-info/LICENSE
dnsprobe-0.2.dist-info/METADATA
dnsprobe-0.2.dist-info/WHEEL
dnsprobe-0.2.dist-info/entry_points.txt
dnsprobe-0.2.dist-info/top_level.txt
dnsprobe-0.2.dist-info/zip-safe
dnsprobe-0.2.dist-info/RECORD
