Metadata-Version: 2.1
Name: dnsprobe
Version: 0.2
Summary: Domain Name System Probe.
Home-page: https://github.com/DNSet/DNSProber/
Author: Mingzhe Zou
Author-email: zoumingzhe@outlook.com
License: GPLv2
Project-URL: Source Code, https://github.com/DNSet/DNSProber/
Project-URL: Bug Tracker, https://github.com/DNSet/DNSProber/issues
Project-URL: Documentation, https://github.com/DNSet/DNSProber/
Platform: any
Classifier: Programming Language :: Python
Classifier: Programming Language :: Python :: 3
Requires-Python: >=3.8
License-File: LICENSE
Requires-Dist: xarg-python >=1.3.1
Requires-Dist: dnspython
Requires-Dist: appdirs
Requires-Dist: strie >=0.2
